rocketgym/__init__.py
rocketgym/constants.py
rocketgym/dashboard.py
rocketgym/environment.py
rocketgym/rocket.py
rocketgym/tvc.py
rocketgym/vector.py
rocketgym/img/bg.png
rocketgym/img/rocket_idle.png
rocketgym/img/rocket_left.png
rocketgym/img/rocket_middle.png
rocketgym/img/rocket_right.png
rocketgym-0.0.13.dist-info/METADATA
rocketgym-0.0.13.dist-info/WHEEL
rocketgym-0.0.13.dist-info/licenses/LICENSE
rocketgym-0.0.13.dist-info/RECORD
