Metadata-Version: 2.1
Name: rocketgym
Version: 0.0.13
Summary: OpenAI Gym for vertical rocket landing. Features full 2D physics engine and works like any other gym.
Project-URL: Homepage, https://github.com/fszewczyk/rocket-landing-rl
Project-URL: Bug Tracker, https://github.com/fszewczyk/rocket-landing-rl/issues
Author-email: Franciszek Szewczyk <szewczyk.franciszek02@gmail.com>
License-File: LICENSE
Classifier: Operating System :: OS Independent
Classifier: Programming Language :: Python :: 3
Requires-Python: >=3.7
Requires-Dist: gym>=0.26.2
Requires-Dist: matplotlib>=3.6.0
Requires-Dist: numpy>=1.23.3
Requires-Dist: opencv-python>=4.6.0.66
Requires-Dist: pandas>=1.5.0
